prixCarburantClient/prixCarburantClient.py
Prix_Carburant_FR_Client-1.0.6.dist-info/METADATA
Prix_Carburant_FR_Client-1.0.6.dist-info/WHEEL
Prix_Carburant_FR_Client-1.0.6.dist-info/entry_points.txt
Prix_Carburant_FR_Client-1.0.6.dist-info/top_level.txt
Prix_Carburant_FR_Client-1.0.6.dist-info/RECORD
