Metadata-Version: 2.1
Name: Prix-Carburant-FR-Client
Version: 1.0.6
Summary: StationEssence client
Home-page: https://github.com/ryann72/essence
Author: Maxime Wantiez, Yann RITTER
Author-email: 
License: MIT
